cand/__init__.py
cand/_version.py
cand/canvas.py
cand/fontant.py
cand/metrics.py
CanD-0.0.2.dist-info/METADATA
CanD-0.0.2.dist-info/WHEEL
CanD-0.0.2.dist-info/top_level.txt
CanD-0.0.2.dist-info/RECORD
