Metadata-Version: 2.1
Name: CanD
Version: 0.0.2
Summary: Create complex layouts for scientific figures in matplotlib
Home-page: https://github.com/mwshinn/cand
Author: Max Shinn
Author-email: m.shinn@ucl.ac.uk
Maintainer: Max Shinn
Maintainer-email: m.shinn@ucl.ac.uk
License: MIT
Platform: UNKNOWN
Classifier: Development Status :: 3 - Alpha
Classifier: Intended Audience :: Science/Research
Classifier: Intended Audience :: Education
Classifier: Framework :: Matplotlib
Classifier: License :: OSI Approved :: MIT License
Classifier: Programming Language :: Python :: 3
Classifier: Topic :: Scientific/Engineering
Classifier: Topic :: Scientific/Engineering :: Visualization
Requires-Python: >=3.5
Requires-Dist: numpy
Requires-Dist: scipy
Requires-Dist: matplotlib
Requires-Dist: paranoid-scientist (>=0.2.1)
Requires-Dist: PyMuPDF (>=1.16.0)
Requires-Dist: Pillow
